CHANGES.rst
CONTRIBUTORS.rst
MANIFEST.in
README.rst
TODO.rst
VERSION
pyproject.toml
setup.cfg
setup.py
docs/LICENSE.GPL
docs/LICENSE.rst
docs/index.rst
src/visaplan/__init__.py
src/visaplan.kitchen.egg-info/PKG-INFO
src/visaplan.kitchen.egg-info/SOURCES.txt
src/visaplan.kitchen.egg-info/dependency_links.txt
src/visaplan.kitchen.egg-info/entry_points.txt
src/visaplan.kitchen.egg-info/namespace_packages.txt
src/visaplan.kitchen.egg-info/not-zip-safe
src/visaplan.kitchen.egg-info/requires.txt
src/visaplan.kitchen.egg-info/top_level.txt
src/visaplan/kitchen/__init__.py
src/visaplan/kitchen/configure.zcml
src/visaplan/kitchen/extract.py
src/visaplan/kitchen/forks.py
src/visaplan/kitchen/ids.py
src/visaplan/kitchen/spoons.py