Metadata-Version: 2.1
Name: visaplan.kitchen
Version: 1.0.5
Summary: A kitchen for (beautiful) soup
Home-page: UNKNOWN
Author: Tobias Herp
Author-email: tobias.herp@visaplan.com
License: GPL version 2
Project-URL: Source, https://github.com/visaplan/kitchen
Project-URL: Tests, https://travis-ci.org/visaplan/kitchen
Project-URL: Documentation, https://pypi.org/project/visaplan.kitchen
Project-URL: Tracker, https://github.com/visaplan/kitchen/issues
Platform: UNKNOWN
Classifier: Environment :: Web Environment
Classifier: Framework :: Plone
Classifier: Framework :: Plone :: 4.3
Classifier: Framework :: Zope2
Classifier: Programming Language :: Python
Classifier: Programming Language :: Python :: 2.7
Classifier: Programming Language :: Python :: 3
Classifier: Intended Audience :: Developers
Classifier: Natural Language :: German
Classifier: Operating System :: OS Independent
Classifier: License :: OSI Approved :: GNU General Public License v2 (GPLv2)
Provides-Extra: test
